{"SerializedFilePath":"C:\\Users\\PB265ZF\\Source\\Repos\\irajushaw23\\Microservice\\Solution1\\WebUI\\obj\\Debug\\net6.0\\project.razor.vs.json","FilePath":"C:\\Users\\PB265ZF\\Source\\Repos\\irajushaw23\\Microservice\\Solution1\\WebUI\\WebUI.csproj","Configuration":{"ConfigurationName":"MVC-3.0","LanguageVersion":"6.0","Extensions":[{"ExtensionName":"MVC-3.0"}]},"ProjectWorkspaceState":{"TagHelpers":[],"CSharpLanguageVersion":1000},"RootNamespace":"WebUI","Documents":[{"FilePath":"C:\\Users\\PB265ZF\\Source\\Repos\\irajushaw23\\Microservice\\Solution1\\WebUI\\Views\\Shared\\_Layout.cshtml","TargetPath":"Views\\Shared\\_Layout.cshtml","FileKind":"mvc"},{"FilePath":"C:\\Users\\PB265ZF\\Source\\Repos\\irajushaw23\\Microservice\\Solution1\\WebUI\\Views\\Users\\Index.cshtml","TargetPath":"Views\\Users\\Index.cshtml","FileKind":"mvc"},{"FilePath":"C:\\Users\\PB265ZF\\Source\\Repos\\irajushaw23\\Microservice\\Solution1\\WebUI\\Views\\Users\\Delete.cshtml","TargetPath":"Views\\Users\\Delete.cshtml","FileKind":"mvc"},{"FilePath":"C:\\Users\\PB265ZF\\Source\\Repos\\irajushaw23\\Microservice\\Solution1\\WebUI\\Views\\UserKYC\\PendingKYC.cshtml","TargetPath":"Views\\UserKYC\\PendingKYC.cshtml","FileKind":"mvc"},{"FilePath":"C:\\Users\\PB265ZF\\Source\\Repos\\irajushaw23\\Microservice\\Solution1\\WebUI\\Views\\Home\\Contact.cshtml","TargetPath":"Views\\Home\\Contact.cshtml","FileKind":"mvc"},{"FilePath":"C:\\Users\\PB265ZF\\Source\\Repos\\irajushaw23\\Microservice\\Solution1\\WebUI\\Views\\Shared\\Error.cshtml","TargetPath":"Views\\Shared\\Error.cshtml","FileKind":"mvc"},{"FilePath":"C:\\Users\\PB265ZF\\Source\\Repos\\irajushaw23\\Microservice\\Solution1\\WebUI\\Views\\UserKYC\\Edit.cshtml","TargetPath":"Views\\UserKYC\\Edit.cshtml","FileKind":"mvc"},{"FilePath":"C:\\Users\\PB265ZF\\Source\\Repos\\irajushaw23\\Microservice\\Solution1\\WebUI\\Views\\_ViewStart.cshtml","TargetPath":"Views\\_ViewStart.cshtml","FileKind":"mvc"},{"FilePath":"C:\\Users\\PB265ZF\\Source\\Repos\\irajushaw23\\Microservice\\Solution1\\WebUI\\Views\\Home\\AboutUs.cshtml","TargetPath":"Views\\Home\\AboutUs.cshtml","FileKind":"mvc"},{"FilePath":"C:\\Users\\PB265ZF\\Source\\Repos\\irajushaw23\\Microservice\\Solution1\\WebUI\\Views\\Users\\Edit.cshtml","TargetPath":"Views\\Users\\Edit.cshtml","FileKind":"mvc"},{"FilePath":"C:\\Users\\PB265ZF\\Source\\Repos\\irajushaw23\\Microservice\\Solution1\\WebUI\\Views\\Shared\\_ValidationScriptsPartial.cshtml","TargetPath":"Views\\Shared\\_ValidationScriptsPartial.cshtml","FileKind":"mvc"},{"FilePath":"C:\\Users\\PB265ZF\\Source\\Repos\\irajushaw23\\Microservice\\Solution1\\WebUI\\Views\\_ViewImports.cshtml","TargetPath":"Views\\_ViewImports.cshtml","FileKind":"mvc"},{"FilePath":"C:\\Users\\PB265ZF\\Source\\Repos\\irajushaw23\\Microservice\\Solution1\\WebUI\\Views\\UserKYC\\ApprovalEdit.cshtml","TargetPath":"Views\\UserKYC\\ApprovalEdit.cshtml","FileKind":"mvc"},{"FilePath":"C:\\Users\\PB265ZF\\Source\\Repos\\irajushaw23\\Microservice\\Solution1\\WebUI\\Views\\UserKYC\\KYCApproval.cshtml","TargetPath":"Views\\UserKYC\\KYCApproval.cshtml","FileKind":"mvc"},{"FilePath":"C:\\Users\\PB265ZF\\Source\\Repos\\irajushaw23\\Microservice\\Solution1\\WebUI\\Views\\Users\\Details.cshtml","TargetPath":"Views\\Users\\Details.cshtml","FileKind":"mvc"},{"FilePath":"C:\\Users\\PB265ZF\\Source\\Repos\\irajushaw23\\Microservice\\Solution1\\WebUI\\Views\\Home\\Privacy.cshtml","TargetPath":"Views\\Home\\Privacy.cshtml","FileKind":"mvc"},{"FilePath":"C:\\Users\\PB265ZF\\Source\\Repos\\irajushaw23\\Microservice\\Solution1\\WebUI\\Views\\Home\\Index.cshtml","TargetPath":"Views\\Home\\Index.cshtml","FileKind":"mvc"},{"FilePath":"C:\\Users\\PB265ZF\\Source\\Repos\\irajushaw23\\Microservice\\Solution1\\WebUI\\Views\\Users\\Create.cshtml","TargetPath":"Views\\Users\\Create.cshtml","FileKind":"mvc"},{"FilePath":"C:\\Users\\PB265ZF\\Source\\Repos\\irajushaw23\\Microservice\\Solution1\\WebUI\\Views\\UserKYC\\KYCStatus.cshtml","TargetPath":"Views\\UserKYC\\KYCStatus.cshtml","FileKind":"mvc"}],"SerializationFormat":"0.3"}